spf.py
spf3-2.0.17.data/scripts/spfquery.py
spf3-2.0.17.data/scripts/type99.py
spf3-2.0.17.dist-info/licenses/LICENSE
spf3-2.0.17.dist-info/METADATA
spf3-2.0.17.dist-info/WHEEL
spf3-2.0.17.dist-info/top_level.txt
spf3-2.0.17.dist-info/RECORD
