Metadata-Version: 2.4
Name: spf3
Version: 2.0.17
Summary: SPF (Sender Policy Framework) implemented in Python.
Home-page: https://github.com/kytta/spf3/
Author: Terence Way
Author-email: terry@wayforward.net
Maintainer: Nikita Karamov
Maintainer-email: me@kytta.dev
License: PSF-2.0
Keywords: spf,email,forgery
Classifier: Development Status :: 5 - Production/Stable
Classifier: Environment :: No Input/Output (Daemon)
Classifier: Intended Audience :: Developers
Classifier: License :: OSI Approved :: Python Software Foundation License
Classifier: Natural Language :: English
Classifier: Operating System :: OS Independent
Classifier: Programming Language :: Python
Classifier: Programming Language :: Python :: 2
Classifier: Programming Language :: Python :: 2.6
Classifier: Programming Language :: Python :: 2.7
Classifier: Programming Language :: Python :: 3
Classifier: Programming Language :: Python :: 3.0
Classifier: Programming Language :: Python :: 3.1
Classifier: Programming Language :: Python :: 3.2
Classifier: Programming Language :: Python :: 3.3
Classifier: Programming Language :: Python :: 3.4
Classifier: Programming Language :: Python :: 3.5
Classifier: Programming Language :: Python :: 3.6
Classifier: Programming Language :: Python :: 3.7
Classifier: Programming Language :: Python :: 3.8
Classifier: Programming Language :: Python :: 3.9
Classifier: Programming Language :: Python :: 3.10
Classifier: Programming Language :: Python :: 3.11
Classifier: Programming Language :: Python :: 3.12
Classifier: Programming Language :: Python :: 3.13
Classifier: Topic :: Communications :: Email :: Filters
Classifier: Topic :: Communications :: Email :: Mail Transport Agents
Classifier: Topic :: Internet :: Name Service (DNS)
Classifier: Topic :: Software Development :: Libraries :: Python Modules
Requires-Python: >=2.6
License-File: LICENSE
Requires-Dist: authres
Requires-Dist: ipaddr; python_version < "3"
Provides-Extra: pydns
Requires-Dist: Py3DNS; python_version >= "3" and extra == "pydns"
Requires-Dist: PyDNS; python_version < "3" and extra == "pydns"
Provides-Extra: dnspython
Requires-Dist: dnspython>=1.16.0; extra == "dnspython"
Dynamic: license-file
